ashlang/__init__.py
ashlang/ash.py
ashlang/ashinterpreter.py
ashlang/ashparser.py
ashlang/ashtest.py
ashlang/ashtranspiler.py
ashlang-0.0.2.dist-info/LICENSE
ashlang-0.0.2.dist-info/METADATA
ashlang-0.0.2.dist-info/WHEEL
ashlang-0.0.2.dist-info/top_level.txt
ashlang-0.0.2.dist-info/RECORD
